Metadata-Version: 1.0
Name: anthill-game-master
Version: 0.2.5
Summary: Game servers hosting & matchmaking service for Anthill platform
Home-page: https://github.com/anthill-platform/anthill-game-master
Author: desertkun
Author-email: desertkun@gmail.com
License: MIT
Platform: UNKNOWN
